README.rst
setup.py
exptools/__init__.py
exptools.egg-info/PKG-INFO
exptools.egg-info/SOURCES.txt
exptools.egg-info/dependency_links.txt
exptools.egg-info/not-zip-safe
exptools.egg-info/requires.txt
exptools.egg-info/top_level.txt
exptools/core/__init__.py
exptools/core/session.py
exptools/core/trial.py
exptools/utils/__init__.py
exptools/utils/config.py