Metadata-Version: 1.0
Name: exptools
Version: 0.2
Summary: Experimental tools of the Knapen lab at the Vrije Universiteit
Home-page: https://github.com/Gilles86/exp_tools
Author: Gilles de Hollander, Tomas Knapen, Daan van Es
Author-email: gilles.de.hollander@gmail.com
License: MIT
Platform: UNKNOWN
